ai_research-0.1.2.dist-info/licenses/LICENSE
air/__init__.py
air/client.py
air/exceptions.py
air/executor.py
air/project.py
air/ws_session.py
ai_research-0.1.2.dist-info/METADATA
ai_research-0.1.2.dist-info/WHEEL
ai_research-0.1.2.dist-info/top_level.txt
ai_research-0.1.2.dist-info/RECORD
