Metadata-Version: 2.4
Name: ai-research
Version: 0.1.2
Summary: Python SDK for the AIR Backend API
Author-email: Boris Bolliet <denario.astropilot.ai@gmail.com>
License: MIT
Project-URL: Homepage, https://github.com/air-ai/air-sdk
Project-URL: Repository, https://github.com/air-ai/air-sdk.git
Classifier: Development Status :: 3 - Alpha
Classifier: License :: OSI Approved :: MIT License
Classifier: Programming Language :: Python :: 3
Classifier: Programming Language :: Python :: 3.10
Classifier: Programming Language :: Python :: 3.11
Classifier: Programming Language :: Python :: 3.12
Requires-Python: >=3.10
License-File: LICENSE
Requires-Dist: httpx>=0.27
Requires-Dist: python-dotenv
Requires-Dist: websockets>=12.0
Provides-Extra: dev
Requires-Dist: pytest>=8.0; extra == "dev"
Dynamic: license-file
